greethelloworld/__init__.py
greethelloworld/hello.py
greethelloworld-1.0.0.dist-info/METADATA
greethelloworld-1.0.0.dist-info/WHEEL
greethelloworld-1.0.0.dist-info/top_level.txt
greethelloworld-1.0.0.dist-info/RECORD
