Metadata-Version: 2.1
Name: greethelloworld
Version: 1.0.0
Summary: Greeting Hello World
Author: Kushal Dulani
Author-email: <kushu9999@gmail.com>
Keywords: python,helloworld,greethelloworld,greethellow,greetinghelloworld
Classifier: Development Status :: 1 - Planning
Classifier: Intended Audience :: Developers
Classifier: Programming Language :: Python :: 3
Classifier: Operating System :: Unix
Classifier: Operating System :: MacOS :: MacOS X
Classifier: Operating System :: Microsoft :: Windows
